{
  "sessionId": "2026-03-19T07-42-19-r9n4if",
  "timestamp": 1773906139574,
  "duration": 10665063,
  "aimsWorked": [
    "9b89766c-46c9-4150-a300-b085b1fcefb5",
    "41706e8a-2a19-43e7-b17f-89b24e9f38d0",
    "2db9fb3e-4a0b-4bbe-b454-f1d5cdecb83a",
    "af58ebb0-1e0f-4f7e-b182-754e918ca30e",
    "93fbe6f4-a11a-45e3-9441-39aaba18e458",
    "4e70b439-0730-448f-a6bc-ac838a1eed59",
    "618b92d0-70cc-434c-b2b5-ee9fcfefc25a"
  ],
  "outcomes": "        fixed.\"}})",
  "patterns": "",
  "lessonsLearned": "",
  "rawReflection": "ion captured from user guidance. Not a release blocker.\"},\"supportedAims\":\n        [\"93fbe6f4-a11a-45e3-9441-39aaba18e458\"],\"tags\":[\"voice\",\"mobile\",\"unclear\",\"future-direction\"]})\n    Created aim with ID: 4e70b439-0730-448f-a6bc-ac838a1eed59 and committed to phase 618b92d0-70cc-434c-b2b5-ee9fcfefc25a\n\n───────────────────────────────────────────────────────────────────────────────────────────────────────────────────────────────────\n\n• I pushed the next release-facing docs cleanup through.\n\n  Changed:\n\n  - added a concise troubleshooting section to README.md\n  - tightened root repo-surface notes in README.md so packages/embedder, packages/mobile, and the top-level exploration folders are\n    explicitly framed as non-core\n  - added packages/embedder/README.md to mark the Python embedder as transitional\n  - added packages/mobile/README.md to mark the Android client as experimental\n  - updated meta/preparing-for-release.md to mark those checklist items done\n\n  I also cleaned the aim graph:\n\n  - marked Verify clean-clone dev/start flows end-to-end and Add preferred-port fallback and resolved-port reporting as human-\n    dependency, since both now depend on real-machine output from you\n  - removed the accidental duplicate optional-packaging unclear aim\n  - added your future voice direction as unclear:\n    Evaluate telephone-style voice API for call-like interaction (4e70b439-0730-448f-a6bc-ac838a1eed59)\n\n  No code tests were needed here because this pass was documentation and aim-graph cleanup only.\n\n  The main remaining release blockers are still:\n\n  - real-machine validation of npm install / npm run dev / npm run start\n  - real-machine validation of node scripts/validate-local-runtime.mjs\n  - the embedder replacement itself in packages/backend/src/embeddings.ts\n\n  If you want, I’ll take the embedder replacement next and work toward removing the Python service from the default architecture\n  rather than waiting on validator output.\n\n \n› Improve documentation in @filename"
}
