{
  "id": "3427a68e-791e-4f59-bc46-bd72d85e6d71",
  "text": "Code refactoring: Split ui.ts mega-store (2547 lines)",
  "description": "ui.ts is too large, split into focused stores:\n- navigation.ts: Column/phase selection, keyboard nav\n- modals.ts: Modal state management\n- graph.ts: Graph view state\n- settings.ts: Project settings, preferences\n\nBenefits: Better maintainability, clearer boundaries, easier testing",
  "tags": [
    "refactoring",
    "technical-debt",
    "code-quality"
  ],
  "supportingConnections": [],
  "supportedAims": [
    "6ad092fc-a69e-475d-8870-30f994a7f6a5"
  ],
  "committedIn": [
    "618b92d0-70cc-434c-b2b5-ee9fcfefc25a"
  ],
  "status": {
    "state": "partially",
    "comment": "Refactor slice 2 complete: extracted project path/history normalization and mutation logic from `stores/ui.ts` into typed helper module `stores/ui/project-helpers.ts` and added focused unit coverage (`stores/ui/project-helpers.spec.ts`). `useUIStore` now delegates setProjectPath + project history actions to helpers, reducing duplication and centralizing path semantics. Verification: `npm run type-check -w frontend` passed; `npm run test:unit -w frontend` passed (14 files, 57 tests).",
    "date": 1771962196783
  },
  "intrinsicValue": 0,
  "cost": 1,
  "loopWeight": 1
}
