{
  "id": "3ccbee81-a78e-45eb-ad8a-f041b2ab32bd",
  "text": "watchdog panel improvements",
  "description": "",
  "tags": [],
  "supportingConnections": [
    {
      "aimId": "15869b9f-fe24-4ea1-8120-d90cbe7d22d5",
      "relativePosition": [
        -1.3142033221195306,
        -2.717233293285979
      ],
      "weight": 1
    },
    {
      "aimId": "ca79c4a6-f077-422b-a1ca-609f95e5cc0d",
      "relativePosition": [
        0.6371834483470304,
        -2.8563308291079283
      ],
      "weight": 1
    },
    {
      "aimId": "9b8f49d4-4dd6-42f6-962f-73df36d9e6c9",
      "relativePosition": [
        0.6832806535791831,
        2.2900558609858144
      ],
      "weight": 1
    },
    {
      "aimId": "570501bf-ac97-43de-a0ff-7495c498b3be",
      "relativePosition": [
        1.9372770697751123,
        -1.5801764315808393
      ],
      "weight": 1
    }
  ],
  "supportedAims": [
    "f2337265-ffc6-4ae8-a421-d6e4d5540210"
  ],
  "committedIn": [],
  "status": {
    "state": "done",
    "comment": "",
    "date": 1766359038135
  },
  "intrinsicValue": 0,
  "cost": 1,
  "loopWeight": 0
}
