{
  "id": "60b12810-91aa-441f-bc3b-08c87a1f077f",
  "text": "ctrl + space for menu (just like the watchdog menu)",
  "description": "",
  "reflections": [],
  "archived": false,
  "tags": [],
  "supportingConnections": [],
  "supportedAims": [
    "c7a6e6fc-7f9b-411a-9696-c60cc10354e0"
  ],
  "committedIn": [],
  "status": {
    "state": "open",
    "comment": "",
    "date": 1783171146326
  },
  "intrinsicValue": 0,
  "cost": 1,
  "loopWeight": 1,
  "duration": 1,
  "costVariance": 0,
  "valueVariance": 0
}
