{
  "id": "f2337265-ffc6-4ae8-a421-d6e4d5540210",
  "text": "ui enhancements",
  "description": "",
  "tags": [],
  "supportingConnections": [
    {
      "aimId": "8775c198-3dc3-4d90-a3e9-55b2067e8ab3",
      "relativePosition": [
        -2.4932480514777335,
        0.1836141437974884
      ],
      "weight": 1
    },
    {
      "aimId": "66af6dde-aab1-49f2-90b6-e42d15a955bf",
      "relativePosition": [
        -2.412551347686576,
        1.721467512745045
      ],
      "weight": 1
    },
    {
      "aimId": "58648df0-e137-418f-a0c9-7fd6f0871452",
      "relativePosition": [
        -2.613533996697072,
        -0.8385180891894372
      ],
      "weight": 1
    },
    {
      "aimId": "8fe1aa4e-d89d-4bc0-b9ab-8fd412d24d3b",
      "relativePosition": [
        1.644397435424491,
        1.4700438449247961
      ],
      "weight": 3
    },
    {
      "aimId": "632f83e7-f22b-4c98-b75b-f1e517bcce98",
      "relativePosition": [
        -1.5766172763993018,
        -1.9401747250593817
      ],
      "weight": 1
    },
    {
      "aimId": "c14dd70b-40cc-4d21-bc51-9b57ef460e38",
      "relativePosition": [
        2.4050947151152613,
        -0.6822898294160917
      ],
      "weight": 1
    },
    {
      "aimId": "793cbea9-7d33-4393-b875-b9d44cca604c",
      "relativePosition": [
        2.070341894294657,
        -1.4013152538698819
      ],
      "weight": 1
    },
    {
      "aimId": "db5d5014-30b7-4362-b84f-57983f38fc8b",
      "relativePosition": [
        -0.48787532358719216,
        -1.6948391905400235
      ],
      "weight": 1
    },
    {
      "aimId": "3ccbee81-a78e-45eb-ad8a-f041b2ab32bd",
      "relativePosition": [
        -1.0584422987047477,
        3.4071975063390645
      ],
      "weight": 1
    },
    {
      "aimId": "c4eba589-3530-4696-901a-5c0aa280ca05",
      "relativePosition": [
        -1.9615438480853897,
        -1.5499502353425294
      ],
      "weight": 1
    },
    {
      "aimId": "c6cdb537-d734-47ff-94da-269cdcbadc3a",
      "relativePosition": [
        -2.4921580095047906,
        0.19785968680133156
      ],
      "weight": 1
    },
    {
      "aimId": "4c18cbb2-c607-40f9-bf03-6a99b15317b7",
      "relativePosition": [
        2.0121609033081644,
        0.4501048242146076
      ],
      "weight": 1
    },
    {
      "aimId": "2e7aa327-e5ee-4622-858e-ab6d1877a009",
      "relativePosition": [
        0.8490655705792972,
        -1.585767657313217
      ],
      "weight": 1
    },
    {
      "aimId": "060b3f53-1854-4fda-a50c-78a98e540288",
      "relativePosition": [
        4.96599410780382,
        1.8086843695929413
      ],
      "weight": 1
    },
    {
      "aimId": "8e63ff9c-f48f-40fe-b7f5-bb94fd0af200",
      "relativePosition": [
        -3.811249306174487,
        -1.559367517709278
      ],
      "weight": 1
    },
    {
      "aimId": "d59d03c1-45dd-48db-98c2-49b61b481f07",
      "relativePosition": [
        6.841971277503797,
        -0.7803536799634095
      ],
      "weight": 1
    },
    {
      "aimId": "338f71c7-44c5-4209-8fa5-84d03e438b83",
      "relativePosition": [
        4.327063455357313,
        -0.5953398799244001
      ],
      "weight": 1
    },
    {
      "aimId": "0eba57d1-6f4f-49a1-bf75-a793792d7d6f",
      "relativePosition": [
        0.5875819970290265,
        -3.023801935848275
      ],
      "weight": 1
    },
    {
      "aimId": "b605abd8-948e-4795-a634-ecc73c9e4a27",
      "relativePosition": [
        -2.4739008100272954,
        0.36029818504440364
      ],
      "weight": 1
    }
  ],
  "supportedAims": [
    "3d868d5b-6ec5-4774-9663-dcceb3e30cb2",
    "33be4e0c-fa52-42ba-a86b-4c209b34e2be",
    "c58ae2b8-9d4b-444e-8c07-5d25e6b6fc1b"
  ],
  "committedIn": [
    "f51f8930-c937-4c66-9db8-d4d313e6d286"
  ],
  "status": {
    "state": "done",
    "comment": "",
    "date": 1768593096135
  },
  "intrinsicValue": 50,
  "cost": 2,
  "loopWeight": 1
}
